README.txt
setup.cfg
setup.py
docs/HISTORY.txt
docs/INSTALL.txt
docs/LICENSE.GPL
docs/LICENSE.txt
medialog/__init__.py
medialog.portlet.placeholder.egg-info/PKG-INFO
medialog.portlet.placeholder.egg-info/SOURCES.txt
medialog.portlet.placeholder.egg-info/dependency_links.txt
medialog.portlet.placeholder.egg-info/entry_points.txt
medialog.portlet.placeholder.egg-info/namespace_packages.txt
medialog.portlet.placeholder.egg-info/not-zip-safe
medialog.portlet.placeholder.egg-info/requires.txt
medialog.portlet.placeholder.egg-info/top_level.txt
medialog/portlet/__init__.py
medialog/portlet/placeholder/__init__.py
medialog/portlet/placeholder/configure.zcml
medialog/portlet/placeholder/placeholderportlet.pt
medialog/portlet/placeholder/placeholderportlet.py
medialog/portlet/placeholder/version.txt
medialog/portlet/placeholder/profiles/default/metadata.xml
medialog/portlet/placeholder/profiles/default/portlets.xml
medialog/portlet/placeholder/tests/__init__.py
medialog/portlet/placeholder/tests/base.py
medialog/portlet/placeholder/tests/test_portlet.py