Metadata-Version: 1.0
Name: medialog.portlet.placeholder
Version: 1.4
Summary: A Simple portlet to show columns
Home-page: http://github.com/espenmn/medialog.portlet.placeholder
Author: Espen Moe-Nilssen
Author-email: espen@medialog.no
License: GPL
Platform: UNKNOWN
Classifier: Framework :: Plone
Classifier: Development Status :: 4 - Beta
Classifier: Framework :: Plone :: 5.0
Classifier: Framework :: Zope2
Classifier: License :: OSI Approved :: GNU General Public License (GPL)
Classifier: Operating System :: OS Independent
Classifier: Programming Language :: Python
